rook_rs/__init__.py
rook_rs/rook_rs.abi3.so
rook_rs-0.1.1.dist-info/METADATA
rook_rs-0.1.1.dist-info/WHEEL
rook_rs.libs/libcom_err-2abe824b.so.2
rook_rs.libs/libcrypto-d3570994.so.10
rook_rs.libs/libgssapi_krb5-497db0c6.so.2
rook_rs.libs/libk5crypto-b1f99d5c.so.3
rook_rs.libs/libkeyutils-dfe70bd6.so.1
rook_rs.libs/libkrb5-fcafa220.so.3
rook_rs.libs/libkrb5support-d0bcff84.so.0
rook_rs.libs/libpcre-9513aab5.so.1
rook_rs.libs/libselinux-0922c95c.so.1
rook_rs.libs/libssl-cd1d6220.so.10
rook_rs-0.1.1.dist-info/RECORD
