Metadata-Version: 2.4
Name: rook-rs
Version: 0.1.1
Classifier: Development Status :: 4 - Beta
Classifier: Intended Audience :: Developers
Classifier: License :: OSI Approved :: Apache Software License
Classifier: Operating System :: OS Independent
Classifier: Programming Language :: Rust
Classifier: Programming Language :: Python :: Implementation :: CPython
Classifier: Programming Language :: Python :: 3
Classifier: Programming Language :: Python :: 3.8
Classifier: Programming Language :: Python :: 3.9
Classifier: Programming Language :: Python :: 3.10
Classifier: Programming Language :: Python :: 3.11
Classifier: Programming Language :: Python :: 3.12
Classifier: Programming Language :: Python :: 3.13
Classifier: Topic :: Scientific/Engineering :: Artificial Intelligence
Classifier: Topic :: Database
Classifier: Typing :: Typed
Summary: Long-term memory layer for AI agents - Python bindings for Rook
Keywords: memory,ai,llm,agents,cognitive,embeddings,vector-store
Home-Page: https://github.com/BangRocket/rook
Author: Joshua Heidorn
License: Apache-2.0
Requires-Python: >=3.8
Project-URL: Documentation, https://github.com/BangRocket/rook#readme
Project-URL: Homepage, https://github.com/BangRocket/rook
Project-URL: Issues, https://github.com/BangRocket/rook/issues
Project-URL: Repository, https://github.com/BangRocket/rook
